demo/__init__.py
demo/demo_clock.py
demo/demo_clock_and_IP.py
demo/demo_emulator.py
demo/demo_forex.py
demo/demo_lcd.py
demo/demo_lcd_backlight.py
demo/demo_lcd_custom_characters.py
demo/demo_lcd_extended_strings.py
demo/demo_lcd_process_bar.py
demo/demo_netmonit.py
demo/demo_scrolling_text.py
demo/demo_tiny_dashboard.py
lcd_16x2/__init__.py
lcd_16x2/drivers/__init__.py
lcd_16x2/drivers/i2c_dev.py
lcd_16x2/emulators/__init__.py
lcd_16x2/emulators/emulator.py
lcd_16x2-0.1.0a15.dist-info/METADATA
lcd_16x2-0.1.0a15.dist-info/WHEEL
lcd_16x2-0.1.0a15.dist-info/top_level.txt
lcd_16x2-0.1.0a15.dist-info/RECORD
