Metadata-Version: 2.4
Name: LCD_16x2
Version: 0.1.0a15
Summary: Python package for interfacing with a 16x2 character I2C liquid-crystal display (LCD).
Home-page: https://github.com/the-raspberry-pi-guy/lcd
Author: Matthew Timmons-Brown (the-raspberry-pi-guy)
Maintainer: https://github.com/the-raspberry-pi-guy/lcd/contributors
Classifier: Programming Language :: Python :: 3
Classifier: Programming Language :: Python :: 3.6
Classifier: Programming Language :: Python :: 3.7
Classifier: Programming Language :: Python :: 3.8
Classifier: Programming Language :: Python :: 3.9
Classifier: Operating System :: POSIX :: Linux
Classifier: Operating System :: Microsoft :: Windows
Classifier: Operating System :: MacOS
Classifier: Operating System :: Unix
Requires-Python: >=3.6
Requires-Dist: requests~=2.32.3
Requires-Dist: beautifulsoup4~=4.13.3
Requires-Dist: setuptools~=78.1.0
Dynamic: author
Dynamic: classifier
Dynamic: description
Dynamic: description-content-type
Dynamic: home-page
Dynamic: maintainer
Dynamic: requires-dist
Dynamic: requires-python
Dynamic: summary
